asteriskinterfacelogger/__init__.py
asteriskinterfacelogger/logging.py
asteriskinterfacelogger-0.8.dist-info/METADATA
asteriskinterfacelogger-0.8.dist-info/WHEEL
asteriskinterfacelogger-0.8.dist-info/top_level.txt
asteriskinterfacelogger-0.8.dist-info/RECORD
